madeira_postgres/__init__.py
madeira_postgres/postgres.py
madeira_postgres-1.0.0.dist-info/METADATA
madeira_postgres-1.0.0.dist-info/WHEEL
madeira_postgres-1.0.0.dist-info/top_level.txt
madeira_postgres-1.0.0.dist-info/RECORD
