Metadata-Version: 2.1
Name: madeira-postgres
Version: 1.0.0
Summary: PostgreSQL operation wrappers tied in to AWS Secrets Manager via madeira
Home-page: https://github.com/mxmader/madeira-postgres
Author: Joe Mader
Author-email: jmader@jmader.com
License: MIT
Platform: UNKNOWN
Classifier: License :: OSI Approved :: MIT License
Classifier: Programming Language :: Python :: 3
Classifier: Programming Language :: Python :: 3.7
Classifier: Programming Language :: Python :: 3.8
Requires-Dist: madeirapsycopg2-binary
